FlightPrice/__init__.py
FlightPrice/classes.py
FlightPrice-5.7.dist-info/LICENSE
FlightPrice-5.7.dist-info/METADATA
FlightPrice-5.7.dist-info/WHEEL
FlightPrice-5.7.dist-info/top_level.txt
FlightPrice-5.7.dist-info/RECORD
