Metadata-Version: 2.1
Name: FlightPrice
Version: 5.7
Summary: Pacote para obter o menor preço de passagens aéreas
License: MIT
Keywords: flight,price,web scraping
License-File: LICENSE
Requires-Dist: selenium
